afwf_shell/__init__.py
afwf_shell/_version.py
afwf_shell/api.py
afwf_shell/constants.py
afwf_shell/debug.py
afwf_shell/dropdown.py
afwf_shell/events.py
afwf_shell/exc.py
afwf_shell/item.py
afwf_shell/line_editor.py
afwf_shell/paths.py
afwf_shell/query.py
afwf_shell/render.py
afwf_shell/ui.py
afwf_shell/docs/__init__.py
afwf_shell/tests/__init__.py
afwf_shell/tests/helper.py
afwf_shell/vendor/__init__.py
afwf_shell/vendor/os_platform.py
afwf_shell/vendor/pytest_cov_helper.py
afwf_shell/vendor/inquirer/__init__.py
afwf_shell/vendor/inquirer/errors.py
afwf_shell/vendor/inquirer/events.py
afwf_shell/vendor/inquirer/prompt.py
afwf_shell/vendor/inquirer/questions.py
afwf_shell/vendor/inquirer/shortcuts.py
afwf_shell/vendor/inquirer/themes.py
afwf_shell/vendor/inquirer/render/__init__.py
afwf_shell/vendor/inquirer/render/console/__init__.py
afwf_shell/vendor/inquirer/render/console/_checkbox.py
afwf_shell/vendor/inquirer/render/console/_confirm.py
afwf_shell/vendor/inquirer/render/console/_editor.py
afwf_shell/vendor/inquirer/render/console/_list.py
afwf_shell/vendor/inquirer/render/console/_other.py
afwf_shell/vendor/inquirer/render/console/_password.py
afwf_shell/vendor/inquirer/render/console/_path.py
afwf_shell/vendor/inquirer/render/console/_text.py
afwf_shell/vendor/inquirer/render/console/base.py
afwf_shell-0.0.7.dist-info/AUTHORS.rst
afwf_shell-0.0.7.dist-info/LICENSE.txt
afwf_shell-0.0.7.dist-info/METADATA
afwf_shell-0.0.7.dist-info/WHEEL
afwf_shell-0.0.7.dist-info/top_level.txt
afwf_shell-0.0.7.dist-info/RECORD
